{"name":"-健身记录","slug":"健身记录","count":2,"postlist":[{"title":"饮食篇：如何在增肌期内完成减脂","uid":"ec5a7aa685a6e54bfdc6ba5d3d2f0f1c","slug":"KneeCare","date":"2023-11-09T07:49:07.760Z","updated":"2024-04-10T07:05:49.432Z","comments":true,"path":"api/articles/KneeCare.json","keywords":null,"cover":"/medias/cover-diet.jpg","text":"写在前面截止到动笔写这篇文章时，我走进健身房开始锻炼正好7个月。在这段时间里，我经历过一周六练，完成两轮三分化的疯狂时期；也经历过弃训半个月，每天胡吃海喝的摆烂...","link":"","photos":[],"count_time":{"symbolsCount":800,"symbolsTime":"1 mins."},"categories":[{"name":"-健身记录","slug":"健身记录","count":2,"path":"api/categories/健身记录.json"}],"tags":[{"name":"-Diet","slug":"Diet","count":2,"path":"api/tags/Diet.json"}],"author":{"name":"ApolloH","slug":"blog-author","avatar":"/medias/avatar.jpg","link":"/","description":"Nature never fails to surprise us <br> </br> 保持热爱，勇往直前","socials":{"github":"https://github.com/ApolloH","twitter":"","stackoverflow":"","wechat":"","qq":"","weibo":"","zhihu":"","csdn":"","juejin":"","customs":{"bilibili":{"icon":"/svg/bilibili.svg","link":"https://space.bilibili.com/398519048"},"Email":{"icon":"/medias/favicon-email.svg","link":"mailto:huangsz.ee@qq.com"}}}}},{"title":"饮食篇：如何在增肌期内完成减脂","uid":"ec5a7aa685a6e54bfdc6ba5d3d2f0f1c","slug":"BodyBuilding","date":"2023-09-27T12:35:28.299Z","updated":"2023-10-04T12:42:59.891Z","comments":true,"path":"api/articles/BodyBuilding.json","keywords":null,"cover":"/medias/cover-diet.jpg","text":"写在前面截止到动笔写这篇文章时，我走进健身房开始锻炼正好7个月。在这段时间里，我经历过一周六练，完成两轮三分化的疯狂时期；也经历过弃训半个月，每天胡吃海喝的摆烂...","link":"","photos":[],"count_time":{"symbolsCount":800,"symbolsTime":"1 mins."},"categories":[{"name":"-健身记录","slug":"健身记录","count":2,"path":"api/categories/健身记录.json"}],"tags":[{"name":"-Diet","slug":"Diet","count":2,"path":"api/tags/Diet.json"}],"author":{"name":"ApolloH","slug":"blog-author","avatar":"/medias/avatar.jpg","link":"/","description":"Nature never fails to surprise us <br> </br> 保持热爱，勇往直前","socials":{"github":"https://github.com/ApolloH","twitter":"","stackoverflow":"","wechat":"","qq":"","weibo":"","zhihu":"","csdn":"","juejin":"","customs":{"bilibili":{"icon":"/svg/bilibili.svg","link":"https://space.bilibili.com/398519048"},"Email":{"icon":"/medias/favicon-email.svg","link":"mailto:huangsz.ee@qq.com"}}}}}]}